DisPass-0.4.0.dist-info/METADATA
DisPass-0.4.0.dist-info/RECORD
DisPass-0.4.0.dist-info/WHEEL
DisPass-0.4.0.dist-info/entry_points.txt
DisPass-0.4.0.dist-info/top_level.txt
dispass/__init__.py
dispass/__main__.py
dispass/algos.py
dispass/cli.py
dispass/dispass.py
dispass/filehandler.py
dispass/gui.py
dispass/interactive_editor.py
dispass/main.py
dispass/commands/__init__.py
dispass/commands/add.py
dispass/commands/disable.py
dispass/commands/enable.py
dispass/commands/generate.py
dispass/commands/gui.py
dispass/commands/help.py
dispass/commands/increment.py
dispass/commands/list.py
dispass/commands/remove.py
dispass/commands/update.py
dispass/commands/version.py
dispass/commands/decorators/__init__.py
dispass/commands/decorators/read_labels.py
dispass/commands/decorators/write_labels.py
