Metadata-Version: 2.1
Name: DisPass
Version: 0.4.0
Summary: Disperse and dispell passwords with a free alternative manager.
Home-page: http://dispass.org/
Author: Benjamin Althues
Author-email: benjamin@babab.nl
License: ISC
Download-URL: http://pypi.python.org/pypi/DisPass/
Platform: any
Classifier: Development Status :: 5 - Production/Stable
Classifier: Environment :: Console
Classifier: Environment :: Console :: Curses
Classifier: Environment :: MacOS X
Classifier: Environment :: Win32 (MS Windows)
Classifier: Environment :: X11 Applications
Classifier: License :: OSI Approved :: ISC License (ISCL)
Classifier: Natural Language :: English
Classifier: Operating System :: OS Independent
Classifier: Programming Language :: Python :: 3 :: Only
Classifier: Programming Language :: Python :: 3.4
Classifier: Programming Language :: Python :: 3.5
Classifier: Programming Language :: Python :: 3.6
Classifier: Topic :: Security :: Cryptography
Classifier: Topic :: Utilities
Requires-Python: >=3.4
Requires-Dist: pycommand
